README.rst
setup.py
digicert_express/__init__.py
digicert_express/config.py
digicert_express/digicert_express.py
digicert_express/request.py
digicert_express/utils.py
digicert_express.egg-info/PKG-INFO
digicert_express.egg-info/SOURCES.txt
digicert_express.egg-info/dependency_links.txt
digicert_express.egg-info/not-zip-safe
digicert_express.egg-info/requires.txt
digicert_express.egg-info/top_level.txt
digicert_express/loggers/__init__.py
digicert_express/parsers/__init__.py
digicert_express/parsers/base.py
digicert_express/platforms/__init__.py
digicert_express/platforms/base_platform.py
digicert_express/platforms/centos_platform.py
digicert_express/platforms/ubuntu_platform.py