Metadata-Version: 1.1
Name: digicert-express
Version: 1.0
Summary: Express Install for DigiCert, Inc.
Home-page: https://github.com/digicert/digicert_express
Author: DigiCert, Inc.
Author-email: support@digicert.com
License: MIT
Platform: UNKNOWN
Classifier: Development Status :: 3 - Alpha
Classifier: Intended Audience :: Information Technology
Classifier: License :: OSI Approved :: MIT License
Classifier: Topic :: Security
Classifier: Programming Language :: Python :: 2.6
Classifier: Programming Language :: Python :: 2.7
